fustor_cli/__init__.py
fustor_cli/main.py
fustor_cli-0.1.2.post3.dist-info/METADATA
fustor_cli-0.1.2.post3.dist-info/WHEEL
fustor_cli-0.1.2.post3.dist-info/entry_points.txt
fustor_cli-0.1.2.post3.dist-info/top_level.txt
fustor_cli-0.1.2.post3.dist-info/RECORD
