Metadata-Version: 2.4
Name: fustor-cli
Version: 0.1.2.post3
Summary: Unified CLI for Fustor services
License-Expression: MIT
Requires-Dist: click>=8.0.0
Requires-Dist: fustor-agent
Requires-Dist: fustor-fusion
Requires-Dist: fustor-registry
Requires-Dist: fustor-common
